dmi_instascraper/VERSION
dmi_instascraper/__init__.py
dmi_instascraper/__main__.py
dmi_instascraper/app.py
dmi_instascraper/banner.png
dmi_instascraper/icon.png
dmi_instascraper/instagram_scraper.py
dmi_instascraper-0.7.0.dist-info/LICENSE
dmi_instascraper-0.7.0.dist-info/METADATA
dmi_instascraper-0.7.0.dist-info/WHEEL
dmi_instascraper-0.7.0.dist-info/top_level.txt
dmi_instascraper-0.7.0.dist-info/RECORD
