Metadata-Version: 2.1
Name: dmi-instascraper
Version: 0.7.0
Summary: A GUI wrapper around instaloader to scrape Instagram hashtags and users with
Home-page: https://github.com/digitalmethodsinitiative/dmi-instascraper
Author: Digital Methods Initiative
Author-email: stijn.peeters@uva.nl
License: UNKNOWN
Platform: UNKNOWN
Classifier: Programming Language :: Python :: 3
Classifier: License :: OSI Approved :: Mozilla Public License 2.0 (MPL 2.0)
Classifier: Operating System :: OS Independent
Requires-Python: >=3.6
Requires-Dist: wxpython
Requires-Dist: instaloader (==4.5.3)
Requires-Dist: setuptools
